setup.cfg
setup.py
creaturecast_scenegraph/__init__.py
creaturecast_scenegraph/__main__.py
creaturecast_scenegraph.egg-info/PKG-INFO
creaturecast_scenegraph.egg-info/SOURCES.txt
creaturecast_scenegraph.egg-info/dependency_links.txt
creaturecast_scenegraph.egg-info/top_level.txt
creaturecast_scenegraph/media/__init__.py
creaturecast_scenegraph/media/fonts/__init__.py
creaturecast_scenegraph/media/icons/__init__.py
creaturecast_scenegraph/models/__init__.py
creaturecast_scenegraph/models/scene_model.py
creaturecast_scenegraph/services/__init__.py
creaturecast_scenegraph/services/get_stylesheet.py
creaturecast_scenegraph/services/server_functions.py
creaturecast_scenegraph/widgets/QProgressIndicator.py
creaturecast_scenegraph/widgets/__init__.py
creaturecast_scenegraph/widgets/node_details_widget.py
creaturecast_scenegraph/widgets/scene_graph_widget.py