Metadata-Version: 1.1
Name: creaturecast-scenegraph
Version: 0.0.5
Summary: A gui for interacting with the a hierarchical scene graph
Home-page: https://github.com/Paxtongerrish/creaturecast_scenegraph.git
Author: Paxton Gerrish
Author-email: creaturecastlabs@gmail.com
License: UNKNOWN
Keywords: sample setuptools development
Platform: UNKNOWN
Classifier: Development Status :: 3 - Alpha
Classifier: Intended Audience :: End Users/Desktop
Classifier: Topic :: Software Development :: Build Tools
Classifier: License :: OSI Approved :: MIT License
Classifier: Programming Language :: Python :: 2.7
